[
  {
    "title": "向海要水、向海要药 中国海洋经济迈向高质量发展",
    "description": "聚焦“十五五”规划纲要，把目光投向蔚蓝的海洋。“十五五”规划纲要对“加强海洋开发利用保护”作出重要部署，提出壮大海水淡化、海洋生物医药等海洋新兴产业。",
    "summary": "聚焦“十五五”规划纲要，把目光投向蔚蓝的海洋。“十五五”规划纲要对“加强海洋开发利用保护”作出重要部署，提出壮大海水淡化、海洋生物医药等海洋新兴产业。",
    "date": "2026-03-15T16:41:38.000Z",
    "link": "https://www.chinanews.com.cn/cj/2026/03-16/10587314.shtml",
    "guid": "https://www.chinanews.com.cn/cj/2026/03-16/10587314.shtml",
    "author": null,
    "comments": null,
    "origlink": null,
    "image": {},
    "source": {},
    "categories": [],
    "enclosures": []
  },
  {
    "title": "中国出台个人贷款新规：禁止隐性收费 明示综合融资成本",
    "description": "中新社北京3月15日电 (陶思阅)为维护个人贷款市场秩序，保护金融消费者合法权益，中国国家金融监督管理总局会同中国人民银行于15日对外公布《个人贷款业务明示综合融资成本规定》(下称《规定》)。",
    "summary": "中新社北京3月15日电 (陶思阅)为维护个人贷款市场秩序，保护金融消费者合法权益，中国国家金融监督管理总局会同中国人民银行于15日对外公布《个人贷款业务明示综合融资成本规定》(下称《规定》)。",
    "date": "2026-03-15T16:34:24.000Z",
    "link": "https://www.chinanews.com.cn/cj/2026/03-16/10587313.shtml",
    "guid": "https://www.chinanews.com.cn/cj/2026/03-16/10587313.shtml",
    "author": null,
    "comments": null,
    "origlink": null,
    "image": {},
    "source": {},
    "categories": [],
    "enclosures": []
  },
  {
    "title": "荐股分成骗局：股票自己编，赔钱就“消失”",
    "description": "2026年伊始，“3·15”晚会收到不少消费者提供的线索：市场上一种名为“荐股做票，盈利五五分成”的股票投资业务，吸引了很多投资者的关注。社交平台上热闹的宣传，微信群里不断出现的炒股盈利故事，对消费者而言，充满着财富的诱惑。",
    "summary": "2026年伊始，“3·15”晚会收到不少消费者提供的线索：市场上一种名为“荐股做票，盈利五五分成”的股票投资业务，吸引了很多投资者的关注。社交平台上热闹的宣传，微信群里不断出现的炒股盈利故事，对消费者而言，充满着财富的诱惑。",
    "date": "2026-03-15T16:14:23.000Z",
    "link": "https://www.chinanews.com.cn/cj/2026/03-16/10587311.shtml",
    "guid": "https://www.chinanews.com.cn/cj/2026/03-16/10587311.shtml",
    "author": null,
    "comments": null,
    "origlink": null,
    "image": {},
    "source": {},
    "categories": [],
    "enclosures": []
  },
  {
    "title": "AI大模型，遭“投毒”",
    "description": "按照业内人士爆料，记者在多个网络平台查询搜索到了一项名为GEO的业务，这些从事该项业务的服务商号称，用户只需支付相应的费用，它就能在各大主流AI大模型里，让客户的产品榜上有名；让客户的商品广告，成为AI模型给出的“标准答案”。",
    "summary": "按照业内人士爆料，记者在多个网络平台查询搜索到了一项名为GEO的业务，这些从事该项业务的服务商号称，用户只需支付相应的费用，它就能在各大主流AI大模型里，让客户的产品榜上有名；让客户的商品广告，成为AI模型给出的“标准答案”。",
    "date": "2026-03-15T16:08:05.000Z",
    "link": "https://www.chinanews.com.cn/cj/2026/03-16/10587310.shtml",
    "guid": "https://www.chinanews.com.cn/cj/2026/03-16/10587310.shtml",
    "author": null,
    "comments": null,
    "origlink": null,
    "image": {},
    "source": {},
    "categories": [],
    "enclosures": []
  },
  {
    "title": "租赁电动自行车“狂飙”！“3·15”点名哈啰租电动车、电驴哥",
    "description": "近期各大直播平台上，一些电商主播们卖力介绍他们对外租赁电动自行车。多位主播在直播间里，公然违反国家的管理规定，大肆宣传其产品超越国家标准，速度超快。",
    "summary": "近期各大直播平台上，一些电商主播们卖力介绍他们对外租赁电动自行车。多位主播在直播间里，公然违反国家的管理规定，大肆宣传其产品超越国家标准，速度超快。",
    "date": "2026-03-15T16:01:38.000Z",
    "link": "https://www.chinanews.com.cn/cj/2026/03-16/10587309.shtml",
    "guid": "https://www.chinanews.com.cn/cj/2026/03-16/10587309.shtml",
    "author": null,
    "comments": null,
    "origlink": null,
    "image": {},
    "source": {},
    "categories": [],
    "enclosures": []
  },
  {
    "title": "最怕315的“骗局”，上“3·15”晚会了！",
    "description": "2026年1月下旬，华中某市举办的一场私域营销行业内部交流会，有上百家相关企业参加。在业内知情人的介绍下，记者顺利进入会场。在交流会上，不少企业代表登台发言，寻找合作伙伴。",
    "summary": "2026年1月下旬，华中某市举办的一场私域营销行业内部交流会，有上百家相关企业参加。在业内知情人的介绍下，记者顺利进入会场。在交流会上，不少企业代表登台发言，寻找合作伙伴。",
    "date": "2026-03-15T15:49:05.000Z",
    "link": "https://www.chinanews.com.cn/cj/2026/03-15/10587301.shtml",
    "guid": "https://www.chinanews.com.cn/cj/2026/03-15/10587301.shtml",
    "author": null,
    "comments": null,
    "origlink": null,
    "image": {},
    "source": {},
    "categories": [],
    "enclosures": []
  },
  {
    "title": "被“3·15”点名，他们连夜回应",
    "description": "15日晚，总台2026年“3·15”晚会重点曝光食品安全、公共安全、金融安全等领域的违法侵权行为。",
    "summary": "15日晚，总台2026年“3·15”晚会重点曝光食品安全、公共安全、金融安全等领域的违法侵权行为。",
    "date": "2026-03-15T15:32:54.000Z",
    "link": "https://www.chinanews.com.cn/cj/2026/03-15/10587297.shtml",
    "guid": "https://www.chinanews.com.cn/cj/2026/03-15/10587297.shtml",
    "author": null,
    "comments": null,
    "origlink": null,
    "image": {},
    "source": {},
    "categories": [],
    "enclosures": []
  },
  {
    "title": "“3·15晚会”曝光完整名单",
    "description": "中央广播电视总台第36届“3·15”晚会于3月15日播出。今年“3·15”晚会聚焦“放心消费 品质生活”的主题，关注食品安全、公共安全、金融安全、广告市场等领域侵害消费者权益的违法行为。",
    "summary": "中央广播电视总台第36届“3·15”晚会于3月15日播出。今年“3·15”晚会聚焦“放心消费 品质生活”的主题，关注食品安全、公共安全、金融安全、广告市场等领域侵害消费者权益的违法行为。",
    "date": "2026-03-15T15:27:34.000Z",
    "link": "https://www.chinanews.com.cn/cj/2026/03-15/10587296.shtml",
    "guid": "https://www.chinanews.com.cn/cj/2026/03-15/10587296.shtml",
    "author": null,
    "comments": null,
    "origlink": null,
    "image": {},
    "source": {},
    "categories": [],
    "enclosures": []
  },
  {
    "title": "漂白鸡爪涉事公司曾参与制定鸡爪标准",
    "description": "中新网3月15日电(记者 吴家驹)总台“3·15”晚会曝光漂白鸡爪，四川省蜀福香食品有限责任公司、重庆市曾巧食品有限公司、成都市明扬食品有限责任公司被点名。天眼查网站显示，这三家公司都曾参与起草标准文件。企业标准信息公共服务平台显示，2025年9月，成都市明扬食品有限责任公司曾公开泡椒畜禽肉制品相关标准。全国团体标准信息平台显示，2023年10月，四川省质量协会发布的某《火锅食材 凤爪》团体标准，重庆曾巧食品有限公司为起草单位之一。",
    "summary": "中新网3月15日电(记者 吴家驹)总台“3·15”晚会曝光漂白鸡爪，四川省蜀福香食品有限责任公司、重庆市曾巧食品有限公司、成都市明扬食品有限责任公司被点名。天眼查网站显示，这三家公司都曾参与起草标准文件。企业标准信息公共服务平台显示，2025年9月，成都市明扬食品有限责任公司曾公开泡椒畜禽肉制品相关标准。全国团体标准信息平台显示，2023年10月，四川省质量协会发布的某《火锅食材 凤爪》团体标准，重庆曾巧食品有限公司为起草单位之一。",
    "date": "2026-03-15T15:20:33.000Z",
    "link": "https://www.chinanews.com.cn/cj/2026/03-15/10587295.shtml",
    "guid": "https://www.chinanews.com.cn/cj/2026/03-15/10587295.shtml",
    "author": null,
    "comments": null,
    "origlink": null,
    "image": {},
    "source": {},
    "categories": [],
    "enclosures": []
  },
  {
    "title": "国家金融监督管理总局 中国人民银行发布《个人贷款业务明示综合融资成本规定》（附答记者问）",
    "description": "为维护个人贷款市场秩序，保护金融消费者合法权益，提升金融服务质效，近日，金融监管总局、中国人民银行联合发布《个人贷款业务明示综合融资成本规定》(以下简称《规定》)，自2026年8月1日起施行。",
    "summary": "为维护个人贷款市场秩序，保护金融消费者合法权益，提升金融服务质效，近日，金融监管总局、中国人民银行联合发布《个人贷款业务明示综合融资成本规定》(以下简称《规定》)，自2026年8月1日起施行。",
    "date": "2026-03-15T15:10:55.000Z",
    "link": "https://www.chinanews.com.cn/cj/2026/03-15/10587294.shtml",
    "guid": "https://www.chinanews.com.cn/cj/2026/03-15/10587294.shtml",
    "author": null,
    "comments": null,
    "origlink": null,
    "image": {},
    "source": {},
    "categories": [],
    "enclosures": []
  },
  {
    "title": "“3·15”晚会曝光的成都3家涉事企业已被责令停产停业",
    "description": "中新网3月15日电 3月15日，成都市市场监督管理局在其官方微信发布通报称，今晚，央视“3·15”晚会曝光“漂白鸡爪”“‘万能神药’外泌体”问题，涉及成都市蜀福香食品有限责任公司、明扬食品有限公司、婕波噻尔生物科技有限公司。成都市委、市政府高度重视，第一时间成立联合调查组开展执法行动，对涉事企业开展全面核查，已责令其停产停业，并全部查封涉事产品及原料，相关情况正在深入调查中。",
    "summary": "中新网3月15日电 3月15日，成都市市场监督管理局在其官方微信发布通报称，今晚，央视“3·15”晚会曝光“漂白鸡爪”“‘万能神药’外泌体”问题，涉及成都市蜀福香食品有限责任公司、明扬食品有限公司、婕波噻尔生物科技有限公司。成都市委、市政府高度重视，第一时间成立联合调查组开展执法行动，对涉事企业开展全面核查，已责令其停产停业，并全部查封涉事产品及原料，相关情况正在深入调查中。",
    "date": "2026-03-15T15:06:59.000Z",
    "link": "https://www.chinanews.com.cn/cj/2026/03-15/10587293.shtml",
    "guid": "https://www.chinanews.com.cn/cj/2026/03-15/10587293.shtml",
    "author": null,
    "comments": null,
    "origlink": null,
    "image": {},
    "source": {},
    "categories": [],
    "enclosures": []
  },
  {
    "title": "天津成立联合调查组调查处置被曝光“灏麟生物”相关问题",
    "description": "3月15日晚，总台“3·15”晚会曝光灏麟(天津)生物科技有限公司相关问题。天津市成立由天津市药监局、天津市卫生健康委、天津市公安局、天津市市场监管委等部门组成的联合调查组，开展调查处置工作，坚决打击违法违规行为，切实维护人民群众合法权益。",
    "summary": "3月15日晚，总台“3·15”晚会曝光灏麟(天津)生物科技有限公司相关问题。天津市成立由天津市药监局、天津市卫生健康委、天津市公安局、天津市市场监管委等部门组成的联合调查组，开展调查处置工作，坚决打击违法违规行为，切实维护人民群众合法权益。",
    "date": "2026-03-15T14:57:42.000Z",
    "link": "https://www.chinanews.com.cn/cj/2026/03-15/10587292.shtml",
    "guid": "https://www.chinanews.com.cn/cj/2026/03-15/10587292.shtml",
    "author": null,
    "comments": null,
    "origlink": null,
    "image": {},
    "source": {},
    "categories": [],
    "enclosures": []
  },
  {
    "title": "专家：AI大模型投毒是新型不正当竞争",
    "description": "中新网3月15日电(记者 王昊)总台“3·15”晚会报道了AI大模型遭“投毒”乱象，山东财大社会治理智能化研究院专家李富民表示，针对商家通过GEO等业务对大模型进行定向训练，引导AI生成特定产品或服务推荐的行为，实质上是一种利用技术手段进行隐蔽营销、虚构事实的新型不正当竞争与消费者误导行为，使消费者在不知情的情况下接收被植入的营销内容，其危害性与违法性需引起高度重视。",
    "summary": "中新网3月15日电(记者 王昊)总台“3·15”晚会报道了AI大模型遭“投毒”乱象，山东财大社会治理智能化研究院专家李富民表示，针对商家通过GEO等业务对大模型进行定向训练，引导AI生成特定产品或服务推荐的行为，实质上是一种利用技术手段进行隐蔽营销、虚构事实的新型不正当竞争与消费者误导行为，使消费者在不知情的情况下接收被植入的营销内容，其危害性与违法性需引起高度重视。",
    "date": "2026-03-15T14:54:23.000Z",
    "link": "https://www.chinanews.com.cn/cj/2026/03-15/10587291.shtml",
    "guid": "https://www.chinanews.com.cn/cj/2026/03-15/10587291.shtml",
    "author": null,
    "comments": null,
    "origlink": null,
    "image": {},
    "source": {},
    "categories": [],
    "enclosures": []
  },
  {
    "title": "中新网评：别让违法商家“过了315再说”",
    "description": "中新网3月15日电 (记者 李雨昕)一句“过了315再说”，透出的不仅是冒牌专家的做贼心虚，更是妄图避避风头再作恶的侥幸心理。",
    "summary": "中新网3月15日电 (记者 李雨昕)一句“过了315再说”，透出的不仅是冒牌专家的做贼心虚，更是妄图避避风头再作恶的侥幸心理。",
    "date": "2026-03-15T14:51:53.000Z",
    "link": "https://www.chinanews.com.cn/cj/2026/03-15/10587289.shtml",
    "guid": "https://www.chinanews.com.cn/cj/2026/03-15/10587289.shtml",
    "author": null,
    "comments": null,
    "origlink": null,
    "image": {},
    "source": {},
    "categories": [],
    "enclosures": []
  },
  {
    "title": "中新网评：别让超标电动自行车成为马路杀手",
    "description": "中新网3月15日电(左登基)总台“3·15”晚会曝光的电动自行车租赁乱象，背后是部分平台和商家无视公共安全的侥幸心理。作为电动自行车租赁行业头部品牌，哈啰租电动车有关人员直言，自身“生意经”就是“借牌生利”。将超标车伪装成国标车出租，是把马路当成试验场，用消费者的生命安全换取暴利。超标车挂着合规牌上路，不仅让新国标形同虚设，更是在给道路交通安全“埋雷”。监管部门必须顺着牌照这条线一查到底，打掉“借牌生利”的生存土壤，别让“狂飙”的超标车成为流动的安全隐患。",
    "summary": "中新网3月15日电(左登基)总台“3·15”晚会曝光的电动自行车租赁乱象，背后是部分平台和商家无视公共安全的侥幸心理。作为电动自行车租赁行业头部品牌，哈啰租电动车有关人员直言，自身“生意经”就是“借牌生利”。将超标车伪装成国标车出租，是把马路当成试验场，用消费者的生命安全换取暴利。超标车挂着合规牌上路，不仅让新国标形同虚设，更是在给道路交通安全“埋雷”。监管部门必须顺着牌照这条线一查到底，打掉“借牌生利”的生存土壤，别让“狂飙”的超标车成为流动的安全隐患。",
    "date": "2026-03-15T14:51:11.000Z",
    "link": "https://www.chinanews.com.cn/cj/2026/03-15/10587290.shtml",
    "guid": "https://www.chinanews.com.cn/cj/2026/03-15/10587290.shtml",
    "author": null,
    "comments": null,
    "origlink": null,
    "image": {},
    "source": {},
    "categories": [],
    "enclosures": []
  },
  {
    "title": "多平台乖媳妇鸡爪下架",
    "description": "中新网3月15日电 3月15日，总台“3·15”晚会报道了网红鸡爪漂白制作等乱象。目前，在淘宝、京东、拼多多等多个电商平台搜索“乖媳妇鸡爪”，已搜索不到相关商品。",
    "summary": "中新网3月15日电 3月15日，总台“3·15”晚会报道了网红鸡爪漂白制作等乱象。目前，在淘宝、京东、拼多多等多个电商平台搜索“乖媳妇鸡爪”，已搜索不到相关商品。",
    "date": "2026-03-15T14:49:23.000Z",
    "link": "https://www.chinanews.com.cn/cj/2026/03-15/10587288.shtml",
    "guid": "https://www.chinanews.com.cn/cj/2026/03-15/10587288.shtml",
    "author": null,
    "comments": null,
    "origlink": null,
    "image": {},
    "source": {},
    "categories": [],
    "enclosures": []
  },
  {
    "title": "重庆市监局回应315鸡爪问题",
    "description": "中新网3月15日电 3月15日，总台“3·15”晚会曝光网红鸡爪问题。15日晚，重庆市市场监督管理局发布情况通报：3月15日晚，央视“3·15”晚会曝光了我市一企业违规使用过氧化氢生产加工凤爪问题。",
    "summary": "中新网3月15日电 3月15日，总台“3·15”晚会曝光网红鸡爪问题。15日晚，重庆市市场监督管理局发布情况通报：3月15日晚，央视“3·15”晚会曝光了我市一企业违规使用过氧化氢生产加工凤爪问题。",
    "date": "2026-03-15T14:46:23.000Z",
    "link": "https://www.chinanews.com.cn/cj/2026/03-15/10587287.shtml",
    "guid": "https://www.chinanews.com.cn/cj/2026/03-15/10587287.shtml",
    "author": null,
    "comments": null,
    "origlink": null,
    "image": {},
    "source": {},
    "categories": [],
    "enclosures": []
  },
  {
    "title": "市监局回应假专家包装公司被315曝光",
    "description": "中新网3月15日电(胡淑娟)3月15日，总台“3·15”晚会曝光“私域营销”5倍暴利围猎老年人乱象。其中，网络视频制作方和策划公司存在肆无忌惮地包装假“专家”的情况，涉及公司包括耍吧文化传播有限公司。当晚，该公司所在地监管部门郑州市巩义市市场监督管理局值班工作人员接电回应称，目前不清楚具体情况，领导也在关注总台“3·15”报道，在集中开会。",
    "summary": "中新网3月15日电(胡淑娟)3月15日，总台“3·15”晚会曝光“私域营销”5倍暴利围猎老年人乱象。其中，网络视频制作方和策划公司存在肆无忌惮地包装假“专家”的情况，涉及公司包括耍吧文化传播有限公司。当晚，该公司所在地监管部门郑州市巩义市市场监督管理局值班工作人员接电回应称，目前不清楚具体情况，领导也在关注总台“3·15”报道，在集中开会。",
    "date": "2026-03-15T14:43:33.000Z",
    "link": "https://www.chinanews.com.cn/cj/2026/03-15/10587286.shtml",
    "guid": "https://www.chinanews.com.cn/cj/2026/03-15/10587286.shtml",
    "author": null,
    "comments": null,
    "origlink": null,
    "image": {},
    "source": {},
    "categories": [],
    "enclosures": []
  },
  {
    "title": "中新网评：要让荐股分成骗局凉拌",
    "description": "中新网3月15日电(记者 查志远)总台“3·15”晚会曝光的荐股分成骗局，再次撕开了某些所谓“投资机构”的画皮。鑫犇科公司无从业资质，靠老板随意挑选股票，用话术诱骗投资者，盈利则分成，亏损就“凉拌”，这是典型的诈骗逻辑。其“联合调研”“风险控制”等承诺，不过是收割投资者的迷魂汤。必须提醒广大投资者：天上不会掉馅饼，凡承诺保底分成者，皆是盯上了你的本金。同时，监管部门应对此类无资质公司重拳出击，清理电话营销、网络推广等诈骗渠道，斩断黑色产业链，守护百姓“钱袋子”。",
    "summary": "中新网3月15日电(记者 查志远)总台“3·15”晚会曝光的荐股分成骗局，再次撕开了某些所谓“投资机构”的画皮。鑫犇科公司无从业资质，靠老板随意挑选股票，用话术诱骗投资者，盈利则分成，亏损就“凉拌”，这是典型的诈骗逻辑。其“联合调研”“风险控制”等承诺，不过是收割投资者的迷魂汤。必须提醒广大投资者：天上不会掉馅饼，凡承诺保底分成者，皆是盯上了你的本金。同时，监管部门应对此类无资质公司重拳出击，清理电话营销、网络推广等诈骗渠道，斩断黑色产业链，守护百姓“钱袋子”。",
    "date": "2026-03-15T14:41:45.000Z",
    "link": "https://www.chinanews.com.cn/cj/2026/03-15/10587285.shtml",
    "guid": "https://www.chinanews.com.cn/cj/2026/03-15/10587285.shtml",
    "author": null,
    "comments": null,
    "origlink": null,
    "image": {},
    "source": {},
    "categories": [],
    "enclosures": []
  },
  {
    "title": "更透明！个人贷款综合融资成本将向借款人明示",
    "description": "新华社北京3月15日电(记者张千千、李延霞)国家金融监督管理总局、中国人民银行3月15日对外发布《个人贷款业务明示综合融资成本规定》，要求贷款人向借款人展示综合融资成本明示表，清晰披露个人贷款息费成本，使个贷各项息费“阳光化”“透明化”。",
    "summary": "新华社北京3月15日电(记者张千千、李延霞)国家金融监督管理总局、中国人民银行3月15日对外发布《个人贷款业务明示综合融资成本规定》，要求贷款人向借款人展示综合融资成本明示表，清晰披露个人贷款息费成本，使个贷各项息费“阳光化”“透明化”。",
    "date": "2026-03-15T14:34:52.000Z",
    "link": "https://www.chinanews.com.cn/cj/2026/03-15/10587284.shtml",
    "guid": "https://www.chinanews.com.cn/cj/2026/03-15/10587284.shtml",
    "author": null,
    "comments": null,
    "origlink": null,
    "image": {},
    "source": {},
    "categories": [],
    "enclosures": []
  },
  {
    "title": "市场监管总局：彻查“3·15”晚会曝光的相关违法行为 维护消费者权益",
    "description": "中新网3月15日电 据“市说新语”微信公众号消息，针对中央广播电视总台“3·15”晚会曝光的“漂白的鸡爪”“增高营销的套路”等涉及市场监管领域的违法行为，市场监管总局迅速启动应急处置机制，部署开展执法行动，查处情况将及时向社会公布。",
    "summary": "中新网3月15日电 据“市说新语”微信公众号消息，针对中央广播电视总台“3·15”晚会曝光的“漂白的鸡爪”“增高营销的套路”等涉及市场监管领域的违法行为，市场监管总局迅速启动应急处置机制，部署开展执法行动，查处情况将及时向社会公布。",
    "date": "2026-03-15T14:19:32.000Z",
    "link": "https://www.chinanews.com.cn/cj/2026/03-15/10587282.shtml",
    "guid": "https://www.chinanews.com.cn/cj/2026/03-15/10587282.shtml",
    "author": null,
    "comments": null,
    "origlink": null,
    "image": {},
    "source": {},
    "categories": [],
    "enclosures": []
  },
  {
    "title": "重拳出击！市场监管总局部署严查酒类产品五大违法违规行为",
    "description": "中新网3月15日电 据“市说新语”微信公众号消息，近日，市场监管总局部署各地市场监管部门开展酒类产品突出问题综合治理工作，严厉打击酒类产品违法违规行为，切实保障人民群众饮食安全和消费权益。",
    "summary": "中新网3月15日电 据“市说新语”微信公众号消息，近日，市场监管总局部署各地市场监管部门开展酒类产品突出问题综合治理工作，严厉打击酒类产品违法违规行为，切实保障人民群众饮食安全和消费权益。",
    "date": "2026-03-15T14:12:59.000Z",
    "link": "https://www.chinanews.com.cn/cj/2026/03-15/10587281.shtml",
    "guid": "https://www.chinanews.com.cn/cj/2026/03-15/10587281.shtml",
    "author": null,
    "comments": null,
    "origlink": null,
    "image": {},
    "source": {},
    "categories": [],
    "enclosures": []
  },
  {
    "title": "荐股分成骗局涉事公司成立不到半年",
    "description": "中新网3月15日电 总台“3·15”晚会曝光荐股分成骗局，遵义市鑫犇科信息咨询有限公司被点名。国家企业信用信息公示系统显示，该公司成立于2025年9月26日。2025年12月30日，该公司地址还曾发生变更。",
    "summary": "中新网3月15日电 总台“3·15”晚会曝光荐股分成骗局，遵义市鑫犇科信息咨询有限公司被点名。国家企业信用信息公示系统显示，该公司成立于2025年9月26日。2025年12月30日，该公司地址还曾发生变更。",
    "date": "2026-03-15T14:04:37.000Z",
    "link": "https://www.chinanews.com.cn/cj/2026/03-15/10587280.shtml",
    "guid": "https://www.chinanews.com.cn/cj/2026/03-15/10587280.shtml",
    "author": null,
    "comments": null,
    "origlink": null,
    "image": {},
    "source": {},
    "categories": [],
    "enclosures": []
  },
  {
    "title": "中新网评：必须斩断给AI投毒之手",
    "description": "中新网3月15日电(记者 李金磊)总台“3#8226;15”晚会曝光AI大模型遭GEO技术“投毒”，黑色产业链触目惊心。不法商家付费投喂虚假信息，把广告包装成AI“标准答案”，堂而皇之登上推荐榜。这不是技术优化，而是明目张胆的数据造假、消费欺诈。AI本应是客观中立的信息助手，如今却沦为不法分子牟利工具，严重破坏市场公平、误导公众决策。监管不能滞后于技术乱象，必须全链条打击、全平台治理，压实平台责任，严厉封堵GEO灰色业务，筑牢AI信息安全防线。绝不能让“付费改答案”成为潜规则，守住技术底线，才能守护数字时代的信任根基。",
    "summary": "中新网3月15日电(记者 李金磊)总台“3#8226;15”晚会曝光AI大模型遭GEO技术“投毒”，黑色产业链触目惊心。不法商家付费投喂虚假信息，把广告包装成AI“标准答案”，堂而皇之登上推荐榜。这不是技术优化，而是明目张胆的数据造假、消费欺诈。AI本应是客观中立的信息助手，如今却沦为不法分子牟利工具，严重破坏市场公平、误导公众决策。监管不能滞后于技术乱象，必须全链条打击、全平台治理，压实平台责任，严厉封堵GEO灰色业务，筑牢AI信息安全防线。绝不能让“付费改答案”成为潜规则，守住技术底线，才能守护数字时代的信任根基。",
    "date": "2026-03-15T14:02:25.000Z",
    "link": "https://www.chinanews.com.cn/cj/2026/03-15/10587279.shtml",
    "guid": "https://www.chinanews.com.cn/cj/2026/03-15/10587279.shtml",
    "author": null,
    "comments": null,
    "origlink": null,
    "image": {},
    "source": {},
    "categories": [],
    "enclosures": []
  },
  {
    "title": "315曝光企业源创基因多项专利被驳回",
    "description": "中新网3月15日电(记者 谢艺观 左雨晴)3月15日，总台“3·15”晚会报道了“网红神药外泌体竟是三无产品”，涉及郑州源创基因科技有限公司。中新网记者向郑州源创基因科技有限公司相关负责人询问，截至发稿前，该负责人未进行回应。据天眼查显示，该公司多项专利被驳回，包括一种免疫细胞的冻存液及冻存方法、一种皮肤成纤维细胞的制备方法等。",
    "summary": "中新网3月15日电(记者 谢艺观 左雨晴)3月15日，总台“3·15”晚会报道了“网红神药外泌体竟是三无产品”，涉及郑州源创基因科技有限公司。中新网记者向郑州源创基因科技有限公司相关负责人询问，截至发稿前，该负责人未进行回应。据天眼查显示，该公司多项专利被驳回，包括一种免疫细胞的冻存液及冻存方法、一种皮肤成纤维细胞的制备方法等。",
    "date": "2026-03-15T13:39:01.000Z",
    "link": "https://www.chinanews.com.cn/cj/2026/03-15/10587276.shtml",
    "guid": "https://www.chinanews.com.cn/cj/2026/03-15/10587276.shtml",
    "author": null,
    "comments": null,
    "origlink": null,
    "image": {},
    "source": {},
    "categories": [],
    "enclosures": []
  },
  {
    "title": "哈啰回应被315晚会点名",
    "description": "中新网3月15日电 总台“3·15”晚会曝光租赁电动自行车，其中包括哈啰租电动车。记者以此询问哈啰客服，对方回复：我们已关注到3.15晚会的相关报道。公司管理层高度重视，已在第一时间成立专项应急工作组，连夜开展全面自查与整改。针对大家关心的“具体问题”，后续公司将通过官方APP等渠道发布详细的处理公告。",
    "summary": "中新网3月15日电 总台“3·15”晚会曝光租赁电动自行车，其中包括哈啰租电动车。记者以此询问哈啰客服，对方回复：我们已关注到3.15晚会的相关报道。公司管理层高度重视，已在第一时间成立专项应急工作组，连夜开展全面自查与整改。针对大家关心的“具体问题”，后续公司将通过官方APP等渠道发布详细的处理公告。",
    "date": "2026-03-15T13:36:19.000Z",
    "link": "https://www.chinanews.com.cn/cj/2026/03-15/10587275.shtml",
    "guid": "https://www.chinanews.com.cn/cj/2026/03-15/10587275.shtml",
    "author": null,
    "comments": null,
    "origlink": null,
    "image": {},
    "source": {},
    "categories": [],
    "enclosures": []
  },
  {
    "title": "增高机构英瑞可公众号小程序被停用",
    "description": "中新网3月15日电(记者 吴家驹)总台“3·15”晚会曝光多个欺骗消费者的增高机构，其中，英瑞可被点名。3月15日晚，记者发现，公众号“英瑞可”因开展的活动涉及法律法规禁止的线上经营项目，已被停止使用。小程序“英瑞可身高体质管理”由于存在欺诈行为，已暂停服务。",
    "summary": "中新网3月15日电(记者 吴家驹)总台“3·15”晚会曝光多个欺骗消费者的增高机构，其中，英瑞可被点名。3月15日晚，记者发现，公众号“英瑞可”因开展的活动涉及法律法规禁止的线上经营项目，已被停止使用。小程序“英瑞可身高体质管理”由于存在欺诈行为，已暂停服务。",
    "date": "2026-03-15T13:34:11.000Z",
    "link": "https://www.chinanews.com.cn/cj/2026/03-15/10587274.shtml",
    "guid": "https://www.chinanews.com.cn/cj/2026/03-15/10587274.shtml",
    "author": null,
    "comments": null,
    "origlink": null,
    "image": {},
    "source": {},
    "categories": [],
    "enclosures": []
  },
  {
    "title": "中新网评：别再为增高智商税买单",
    "description": "中新网3月15日电(左登基)“给骨骼装上生长加速器”“无效敢全额退款”，总台“3·15”晚会曝光的“增高”骗局，将一众商家精心包装的“增高神话”彻底击碎。从宣称用仪器刺激骨骺线的安立身，到鼓吹声波技术的德脊瑞，再到连玄学都敢塞进套餐的英瑞可，这些商家不仅利用了家长对孩子身高的深切期盼，更将伪科学当作摇钱树，行径之荒唐，吃相之难看令人咋舌。这提醒家长们，别再为孩子增高的智商税买单，也别让科学的缺失成为骗局的温床。守住钱袋，更要守住常识。",
    "summary": "中新网3月15日电(左登基)“给骨骼装上生长加速器”“无效敢全额退款”，总台“3·15”晚会曝光的“增高”骗局，将一众商家精心包装的“增高神话”彻底击碎。从宣称用仪器刺激骨骺线的安立身，到鼓吹声波技术的德脊瑞，再到连玄学都敢塞进套餐的英瑞可，这些商家不仅利用了家长对孩子身高的深切期盼，更将伪科学当作摇钱树，行径之荒唐，吃相之难看令人咋舌。这提醒家长们，别再为孩子增高的智商税买单，也别让科学的缺失成为骗局的温床。守住钱袋，更要守住常识。",
    "date": "2026-03-15T13:27:58.000Z",
    "link": "https://www.chinanews.com.cn/cj/2026/03-15/10587273.shtml",
    "guid": "https://www.chinanews.com.cn/cj/2026/03-15/10587273.shtml",
    "author": null,
    "comments": null,
    "origlink": null,
    "image": {},
    "source": {},
    "categories": [],
    "enclosures": []
  },
  {
    "title": "中新网评：不能让医学专家成为坑老帮凶",
    "description": "中新网3月15日电 (记者 查志远)据总台“3·15”晚会报道，一些不良企业和私域营销公司合作制作虚假课程讲座，利用私域隐蔽性，夸大药效、虚构身份，以数倍暴利榨取老人养老钱。从“医学专家”可花钱包装，到从业者扬言“过了315再说”，这种刻意规避监管、专坑老年人的骗术，暴露了某些商家毫无底线的投机心理。对此，监管部门必须露头就打，不给“躲猫猫”任何喘息空间。也提醒广大子女，多关注老人网络动态，别让私域成为坑老的盲区。",
    "summary": "中新网3月15日电 (记者 查志远)据总台“3·15”晚会报道，一些不良企业和私域营销公司合作制作虚假课程讲座，利用私域隐蔽性，夸大药效、虚构身份，以数倍暴利榨取老人养老钱。从“医学专家”可花钱包装，到从业者扬言“过了315再说”，这种刻意规避监管、专坑老年人的骗术，暴露了某些商家毫无底线的投机心理。对此，监管部门必须露头就打，不给“躲猫猫”任何喘息空间。也提醒广大子女，多关注老人网络动态，别让私域成为坑老的盲区。",
    "date": "2026-03-15T13:24:36.000Z",
    "link": "https://www.chinanews.com.cn/cj/2026/03-15/10587272.shtml",
    "guid": "https://www.chinanews.com.cn/cj/2026/03-15/10587272.shtml",
    "author": null,
    "comments": null,
    "origlink": null,
    "image": {},
    "source": {},
    "categories": [],
    "enclosures": []
  },
  {
    "title": "四川药监回应企业宣称外泌体治疗疾病",
    "description": "中新网3月15日电(记者 谢艺观)3月15日，总台“3·15”晚会报道了“网红神药外泌体竟是三无产品”，涉及四川成都市婕波噻尔生物科技有限公司。对此，四川省药监局工作人员表示，目前正在现场核查相关资料，涉事公司负责人尚未到场。",
    "summary": "中新网3月15日电(记者 谢艺观)3月15日，总台“3·15”晚会报道了“网红神药外泌体竟是三无产品”，涉及四川成都市婕波噻尔生物科技有限公司。对此，四川省药监局工作人员表示，目前正在现场核查相关资料，涉事公司负责人尚未到场。",
    "date": "2026-03-15T13:16:52.000Z",
    "link": "https://www.chinanews.com.cn/cj/2026/03-15/10587270.shtml",
    "guid": "https://www.chinanews.com.cn/cj/2026/03-15/10587270.shtml",
    "author": null,
    "comments": null,
    "origlink": null,
    "image": {},
    "source": {},
    "categories": [],
    "enclosures": []
  }
]