[
  {
    "title": "版权纠纷绊住Seedance 2.0",
    "description": "中新网北京3月18日电(左宇坤 胡淑娟)字节跳动被迫按下了备受瞩目的Seedance 2.0全球发布“暂停键”。",
    "summary": "中新网北京3月18日电(左宇坤 胡淑娟)字节跳动被迫按下了备受瞩目的Seedance 2.0全球发布“暂停键”。",
    "date": "2026-03-18T15:27:47.000Z",
    "link": "https://www.chinanews.com.cn/cj/2026/03-18/10589101.shtml",
    "guid": "https://www.chinanews.com.cn/cj/2026/03-18/10589101.shtml",
    "author": null,
    "comments": null,
    "origlink": null,
    "image": {},
    "source": {},
    "categories": [],
    "enclosures": []
  },
  {
    "title": "中签概率约1.07% “苏超”南京赛区小微企业商务遴选摇号结果出炉",
    "description": "中新网南京3月18日电 (记者 朱晓颖)“南京发布”18日公布，2026江苏省城市足球联赛(即“苏超”)(南京赛区)小微企业商务遴选摇号结果出炉。560家企业报名，通过摇号产生6家拟中选和12家备选合作企业。遴选中签概率约1.07%。",
    "summary": "中新网南京3月18日电 (记者 朱晓颖)“南京发布”18日公布，2026江苏省城市足球联赛(即“苏超”)(南京赛区)小微企业商务遴选摇号结果出炉。560家企业报名，通过摇号产生6家拟中选和12家备选合作企业。遴选中签概率约1.07%。",
    "date": "2026-03-18T14:03:00.000Z",
    "link": "https://www.chinanews.com.cn/cj/2026/03-18/10589088.shtml",
    "guid": "https://www.chinanews.com.cn/cj/2026/03-18/10589088.shtml",
    "author": null,
    "comments": null,
    "origlink": null,
    "image": {},
    "source": {},
    "categories": [],
    "enclosures": []
  },
  {
    "title": "海南封关看变化：首季度洋浦港多项指标实现全面增长",
    "description": "中新网海南洋浦3月18日电(梁辰)2025年12月18日海南自贸港全岛封关运作启动后，洋浦港作为海南自贸港对外开放重要门户和核心航运枢纽，在封关首季度实现了运行高效、货运量攀升、政策红利加速释放的良好态势。",
    "summary": "中新网海南洋浦3月18日电(梁辰)2025年12月18日海南自贸港全岛封关运作启动后，洋浦港作为海南自贸港对外开放重要门户和核心航运枢纽，在封关首季度实现了运行高效、货运量攀升、政策红利加速释放的良好态势。",
    "date": "2026-03-18T14:02:30.000Z",
    "link": "https://www.chinanews.com.cn/cj/2026/03-18/10589085.shtml",
    "guid": "https://www.chinanews.com.cn/cj/2026/03-18/10589085.shtml",
    "author": null,
    "comments": null,
    "origlink": null,
    "image": {},
    "source": {},
    "categories": [],
    "enclosures": []
  },
  {
    "title": "机械化助力农业生产“加速跑” 多地“新”潮澎湃“智”绘“科技春耕图”",
    "description": "央视网消息：人勤春来早，春耕正当时。眼下，江西省的春耕生产全面展开，各地持续加大农机投入，以机械化助力农业生产，全力保障粮食稳产提质。",
    "summary": "央视网消息：人勤春来早，春耕正当时。眼下，江西省的春耕生产全面展开，各地持续加大农机投入，以机械化助力农业生产，全力保障粮食稳产提质。",
    "date": "2026-03-18T13:53:01.000Z",
    "link": "https://www.chinanews.com.cn/cj/2026/03-18/10589081.shtml",
    "guid": "https://www.chinanews.com.cn/cj/2026/03-18/10589081.shtml",
    "author": null,
    "comments": null,
    "origlink": null,
    "image": {},
    "source": {},
    "categories": [],
    "enclosures": []
  },
  {
    "title": "库克现身成都出席苹果公司成立50周年庆典",
    "description": "中新网成都3月18日电 (单鹏 程兆)18日下午，成都太古里苹果零售店外人头攒动。15时许，苹果公司首席执行官蒂姆·库克现身，他走上舞台与观众亲切打招呼。此次活动是苹果公司成立50周年系列庆祝活动的全球第二站、亚太首站，引发广泛关注。",
    "summary": "中新网成都3月18日电 (单鹏 程兆)18日下午，成都太古里苹果零售店外人头攒动。15时许，苹果公司首席执行官蒂姆·库克现身，他走上舞台与观众亲切打招呼。此次活动是苹果公司成立50周年系列庆祝活动的全球第二站、亚太首站，引发广泛关注。",
    "date": "2026-03-18T13:49:23.000Z",
    "link": "https://www.chinanews.com.cn/cj/2026/03-18/10589077.shtml",
    "guid": "https://www.chinanews.com.cn/cj/2026/03-18/10589077.shtml",
    "author": null,
    "comments": null,
    "origlink": null,
    "image": {},
    "source": {},
    "categories": [],
    "enclosures": []
  },
  {
    "title": "江苏拿出系列创新举措推进城市高质量发展",
    "description": "中新网南京3月18日电 (记者 朱晓颖)江苏省人民政府18日在南京召开新闻发布会，各部门相关负责人就近日中共江苏省委、省政府印发的《推进江苏城市高质量发展行动方案》(简称《行动方案》)进行解读。据介绍，《行动方案》提出了建立可持续的城市建设运营投融资机制等创新举措。",
    "summary": "中新网南京3月18日电 (记者 朱晓颖)江苏省人民政府18日在南京召开新闻发布会，各部门相关负责人就近日中共江苏省委、省政府印发的《推进江苏城市高质量发展行动方案》(简称《行动方案》)进行解读。据介绍，《行动方案》提出了建立可持续的城市建设运营投融资机制等创新举措。",
    "date": "2026-03-18T13:49:17.000Z",
    "link": "https://www.chinanews.com.cn/cj/2026/03-18/10589076.shtml",
    "guid": "https://www.chinanews.com.cn/cj/2026/03-18/10589076.shtml",
    "author": null,
    "comments": null,
    "origlink": null,
    "image": {},
    "source": {},
    "categories": [],
    "enclosures": []
  },
  {
    "title": "第51届日内瓦国际发明展鄂托克螺旋藻双项目摘金纳银",
    "description": "中新网鄂尔多斯3月18日电 (记者 李爱平)内蒙古自治区鄂尔多斯市鄂托克旗工信和科技局18日发布消息称，近日，第51届日内瓦国际发明展结果公布，浙江大学—鄂尔多斯市鄂托克旗生物医药联合研究中心主任周民教授团队参展的两个项目分别荣获金奖、银奖。",
    "summary": "中新网鄂尔多斯3月18日电 (记者 李爱平)内蒙古自治区鄂尔多斯市鄂托克旗工信和科技局18日发布消息称，近日，第51届日内瓦国际发明展结果公布，浙江大学—鄂尔多斯市鄂托克旗生物医药联合研究中心主任周民教授团队参展的两个项目分别荣获金奖、银奖。",
    "date": "2026-03-18T13:26:12.000Z",
    "link": "https://www.chinanews.com.cn/cj/2026/03-18/10589061.shtml",
    "guid": "https://www.chinanews.com.cn/cj/2026/03-18/10589061.shtml",
    "author": null,
    "comments": null,
    "origlink": null,
    "image": {},
    "source": {},
    "categories": [],
    "enclosures": []
  },
  {
    "title": "2025年青海社会融资规模增加459.7亿元",
    "description": "中新网西宁3月18日电 (祁增蓓)18日，记者从2025年青海省金融运行情况暨金融政策支持青海高质量发展新闻发布会获悉，2025年，青海省社会融资规模增加459.7亿元，同比多增373.5亿元，为“十四五”期间的次高水平。",
    "summary": "中新网西宁3月18日电 (祁增蓓)18日，记者从2025年青海省金融运行情况暨金融政策支持青海高质量发展新闻发布会获悉，2025年，青海省社会融资规模增加459.7亿元，同比多增373.5亿元，为“十四五”期间的次高水平。",
    "date": "2026-03-18T13:22:07.000Z",
    "link": "https://www.chinanews.com.cn/cj/2026/03-18/10589053.shtml",
    "guid": "https://www.chinanews.com.cn/cj/2026/03-18/10589053.shtml",
    "author": null,
    "comments": null,
    "origlink": null,
    "image": {},
    "source": {},
    "categories": [],
    "enclosures": []
  },
  {
    "title": "由几天缩至20小时 同江铁路口岸刷新进口铜精矿通关速度",
    "description": "中新网佳木斯3月18日电(姜辉 乔冬梅)日前，一列满载进口铜精矿的列车顺利抵达同江铁路口岸。这是落户同江市的西旺冶金(同江)有限责任公司首票进口业务，货重3788.05吨，货值1.04亿元。从列车进站到货物放行，全程仅用约20小时，刷新了同江铁路口岸进口铜精矿通关速度。",
    "summary": "中新网佳木斯3月18日电(姜辉 乔冬梅)日前，一列满载进口铜精矿的列车顺利抵达同江铁路口岸。这是落户同江市的西旺冶金(同江)有限责任公司首票进口业务，货重3788.05吨，货值1.04亿元。从列车进站到货物放行，全程仅用约20小时，刷新了同江铁路口岸进口铜精矿通关速度。",
    "date": "2026-03-18T13:22:01.000Z",
    "link": "https://www.chinanews.com.cn/cj/2026/03-18/10589052.shtml",
    "guid": "https://www.chinanews.com.cn/cj/2026/03-18/10589052.shtml",
    "author": null,
    "comments": null,
    "origlink": null,
    "image": {},
    "source": {},
    "categories": [],
    "enclosures": []
  },
  {
    "title": "海归青年与“老数控”的创业记：接力跑出智造加速度",
    "description": "中新网丽水3月18日电(蓝伊旎 黄晓俊)春日的午后，位于浙江丽水经济技术开发区的高崎智能装备(丽水)有限公司(以下简称“高崎智能”)车间里机器轰鸣。在一张普通办公桌前，32岁的总经理施贻特电话不断——新客户下单、老客户催单、展会跟进、技术咨询，几乎没有停歇。",
    "summary": "中新网丽水3月18日电(蓝伊旎 黄晓俊)春日的午后，位于浙江丽水经济技术开发区的高崎智能装备(丽水)有限公司(以下简称“高崎智能”)车间里机器轰鸣。在一张普通办公桌前，32岁的总经理施贻特电话不断——新客户下单、老客户催单、展会跟进、技术咨询，几乎没有停歇。",
    "date": "2026-03-18T12:40:55.000Z",
    "link": "https://www.chinanews.com.cn/cj/2026/03-18/10589023.shtml",
    "guid": "https://www.chinanews.com.cn/cj/2026/03-18/10589023.shtml",
    "author": null,
    "comments": null,
    "origlink": null,
    "image": {},
    "source": {},
    "categories": [],
    "enclosures": []
  },
  {
    "title": "金蝶2025年云服务收入占比超八成 AI成核心增长动力",
    "description": "中新社香港3月18日电 (记者 戴小橦)中国头部企业云服务厂商金蝶国际软件集团有限公司(简称“金蝶”)18日在港公布2025年年度业绩。期内，集团总收入约70.06亿元(人民币，下同)，同比增长12%，经调整后净利润约2.32亿元，成功扭亏为盈；云服务收入约57.82亿元，占比82.5%。",
    "summary": "中新社香港3月18日电 (记者 戴小橦)中国头部企业云服务厂商金蝶国际软件集团有限公司(简称“金蝶”)18日在港公布2025年年度业绩。期内，集团总收入约70.06亿元(人民币，下同)，同比增长12%，经调整后净利润约2.32亿元，成功扭亏为盈；云服务收入约57.82亿元，占比82.5%。",
    "date": "2026-03-18T12:40:11.000Z",
    "link": "https://www.chinanews.com.cn/cj/2026/03-18/10589025.shtml",
    "guid": "https://www.chinanews.com.cn/cj/2026/03-18/10589025.shtml",
    "author": null,
    "comments": null,
    "origlink": null,
    "image": {},
    "source": {},
    "categories": [],
    "enclosures": []
  },
  {
    "title": "新疆新能源外送电量突破3000亿千瓦时",
    "description": "中新社乌鲁木齐3月18日电 (胡嘉琛 余艳春 李长峰)记者18日从新疆电力交易中心有限公司获悉，自2010年启动疆电外送以来，截至目前，新疆新能源累计外送电量超3043亿千瓦时。",
    "summary": "中新社乌鲁木齐3月18日电 (胡嘉琛 余艳春 李长峰)记者18日从新疆电力交易中心有限公司获悉，自2010年启动疆电外送以来，截至目前，新疆新能源累计外送电量超3043亿千瓦时。",
    "date": "2026-03-18T12:39:37.000Z",
    "link": "https://www.chinanews.com.cn/cj/2026/03-18/10589027.shtml",
    "guid": "https://www.chinanews.com.cn/cj/2026/03-18/10589027.shtml",
    "author": null,
    "comments": null,
    "origlink": null,
    "image": {},
    "source": {},
    "categories": [],
    "enclosures": []
  },
  {
    "title": "海南产经新观察：澄迈打造AI短剧产业出海“桥头堡”",
    "description": "中新网海南澄迈3月18日电 (陈英清)海南AI短剧出海产业基地成立仪式18日在海南生态软件园举行。作为海南首个专业聚焦AI短剧出海的产业基地，其落地是海南自贸港数字文化产业发展、推动文化出海的重要举措，助力澄迈打造立足海南、服务全国、面向全球的AI短剧产业集聚高地与出海“桥头堡”。",
    "summary": "中新网海南澄迈3月18日电 (陈英清)海南AI短剧出海产业基地成立仪式18日在海南生态软件园举行。作为海南首个专业聚焦AI短剧出海的产业基地，其落地是海南自贸港数字文化产业发展、推动文化出海的重要举措，助力澄迈打造立足海南、服务全国、面向全球的AI短剧产业集聚高地与出海“桥头堡”。",
    "date": "2026-03-18T12:39:01.000Z",
    "link": "https://www.chinanews.com.cn/cj/2026/03-18/10589014.shtml",
    "guid": "https://www.chinanews.com.cn/cj/2026/03-18/10589014.shtml",
    "author": null,
    "comments": null,
    "origlink": null,
    "image": {},
    "source": {},
    "categories": [],
    "enclosures": []
  },
  {
    "title": "上海金融监管局：2025年累计受理各类金融纠纷案件11.78万件",
    "description": "中新网上海3月18日电 (高志苗)记者18日从上海金融监管局获悉，2025年，上海金融监管局指导辖内调解组织累计受理各类金融纠纷案件11.78万件，完成调解7.37万件，调解成功率达74.36%。",
    "summary": "中新网上海3月18日电 (高志苗)记者18日从上海金融监管局获悉，2025年，上海金融监管局指导辖内调解组织累计受理各类金融纠纷案件11.78万件，完成调解7.37万件，调解成功率达74.36%。",
    "date": "2026-03-18T11:54:28.000Z",
    "link": "https://www.chinanews.com.cn/cj/2026/03-18/10588995.shtml",
    "guid": "https://www.chinanews.com.cn/cj/2026/03-18/10588995.shtml",
    "author": null,
    "comments": null,
    "origlink": null,
    "image": {},
    "source": {},
    "categories": [],
    "enclosures": []
  },
  {
    "title": "数智赋能破困局 广西林权登记跑出“加速度”",
    "description": "中新网南宁3月18日电 (记者 陈溯)广西作为我国南方重要生态屏障和林业大区，林地面积达2.42亿亩，占全区国土面积的68%，林业总产值突破万亿元，位居全国首位。深化集体林权制度改革全面推开以来，广西以林权登记为切入点，推动数智赋能与机制创新深度融合，探索出一条低成本、高效率、可持续的林权登记提质增效新路径。",
    "summary": "中新网南宁3月18日电 (记者 陈溯)广西作为我国南方重要生态屏障和林业大区，林地面积达2.42亿亩，占全区国土面积的68%，林业总产值突破万亿元，位居全国首位。深化集体林权制度改革全面推开以来，广西以林权登记为切入点，推动数智赋能与机制创新深度融合，探索出一条低成本、高效率、可持续的林权登记提质增效新路径。",
    "date": "2026-03-18T11:53:38.000Z",
    "link": "https://www.chinanews.com.cn/cj/2026/03-18/10588992.shtml",
    "guid": "https://www.chinanews.com.cn/cj/2026/03-18/10588992.shtml",
    "author": null,
    "comments": null,
    "origlink": null,
    "image": {},
    "source": {},
    "categories": [],
    "enclosures": []
  },
  {
    "title": "海外客商齐聚浙江瑞安“抢设备” “前展后厂”促合作",
    "description": "中新网温州3月18日电(周健 项颖 蔡伟)“从去年开始一直在中国各地寻找这样的生产设备，今天在展会上看到，太惊喜了！”3月17日至3月19日，首届中国(瑞安)国际印刷包装工业展览会在浙江温州瑞安市举行，来自南非的客商雷吉诺德(Reginald)如愿找到了心仪的智能纸杯机设备。",
    "summary": "中新网温州3月18日电(周健 项颖 蔡伟)“从去年开始一直在中国各地寻找这样的生产设备，今天在展会上看到，太惊喜了！”3月17日至3月19日，首届中国(瑞安)国际印刷包装工业展览会在浙江温州瑞安市举行，来自南非的客商雷吉诺德(Reginald)如愿找到了心仪的智能纸杯机设备。",
    "date": "2026-03-18T11:53:24.000Z",
    "link": "https://www.chinanews.com.cn/cj/2026/03-18/10588991.shtml",
    "guid": "https://www.chinanews.com.cn/cj/2026/03-18/10588991.shtml",
    "author": null,
    "comments": null,
    "origlink": null,
    "image": {},
    "source": {},
    "categories": [],
    "enclosures": []
  },
  {
    "title": "2026国际可持续水产养殖大会在福州开幕",
    "description": "中新社福州3月18日电 (郑江洛)由中国渔业协会与联合国粮食及农业组织联合主办的2026国际可持续水产养殖大会18日在福州市开幕。",
    "summary": "中新社福州3月18日电 (郑江洛)由中国渔业协会与联合国粮食及农业组织联合主办的2026国际可持续水产养殖大会18日在福州市开幕。",
    "date": "2026-03-18T11:52:18.000Z",
    "link": "https://www.chinanews.com.cn/cj/2026/03-18/10588988.shtml",
    "guid": "https://www.chinanews.com.cn/cj/2026/03-18/10588988.shtml",
    "author": null,
    "comments": null,
    "origlink": null,
    "image": {},
    "source": {},
    "categories": [],
    "enclosures": []
  },
  {
    "title": "“蒙”字标品牌：174家企业1600余种产品获认证",
    "description": "中新网呼和浩特3月18日电 (记者 刘文华)18日，2026年“蒙”字标品牌建设推进会在呼和浩特召开。会上公布的数据显示，“蒙”字标品牌认证体系已覆盖174家企业、1600余种产品，发布认证标准154项，成为连接内蒙古优质产品与全国消费市场的一张公共品牌名片。",
    "summary": "中新网呼和浩特3月18日电 (记者 刘文华)18日，2026年“蒙”字标品牌建设推进会在呼和浩特召开。会上公布的数据显示，“蒙”字标品牌认证体系已覆盖174家企业、1600余种产品，发布认证标准154项，成为连接内蒙古优质产品与全国消费市场的一张公共品牌名片。",
    "date": "2026-03-18T11:40:47.000Z",
    "link": "https://www.chinanews.com.cn/cj/2026/03-18/10588966.shtml",
    "guid": "https://www.chinanews.com.cn/cj/2026/03-18/10588966.shtml",
    "author": null,
    "comments": null,
    "origlink": null,
    "image": {},
    "source": {},
    "categories": [],
    "enclosures": []
  },
  {
    "title": "京津中关村科技城再添动能 22个项目落户天津宝坻",
    "description": "中新网天津3月18日电 (薛淳月 周亚强)18日下午，京津中关村科技城推介会暨重点项目签约仪式在天津举行。现场签约22个优质产业项目，涵盖新材料、智能网联汽车、低空经济等多个主导产业，并正式发布天津市宝坻区首批应用场景需求清单，以场景开放激活创新动能，推动科技城从“给政策”向“给机会”升级。",
    "summary": "中新网天津3月18日电 (薛淳月 周亚强)18日下午，京津中关村科技城推介会暨重点项目签约仪式在天津举行。现场签约22个优质产业项目，涵盖新材料、智能网联汽车、低空经济等多个主导产业，并正式发布天津市宝坻区首批应用场景需求清单，以场景开放激活创新动能，推动科技城从“给政策”向“给机会”升级。",
    "date": "2026-03-18T11:38:57.000Z",
    "link": "https://www.chinanews.com.cn/cj/2026/03-18/10588978.shtml",
    "guid": "https://www.chinanews.com.cn/cj/2026/03-18/10588978.shtml",
    "author": null,
    "comments": null,
    "origlink": null,
    "image": {},
    "source": {},
    "categories": [],
    "enclosures": []
  },
  {
    "title": "人工智能赋能新型工业化 江苏盐城推动“人工智能+”发展",
    "description": "中新网盐城3月18日电(记者 谷华)18日，江苏盐城召开全市人工智能赋能新型工业化推进会，以“人工智能赋能新型工业化”为主题，推动人工智能和制造业深度融合。",
    "summary": "中新网盐城3月18日电(记者 谷华)18日，江苏盐城召开全市人工智能赋能新型工业化推进会，以“人工智能赋能新型工业化”为主题，推动人工智能和制造业深度融合。",
    "date": "2026-03-18T11:38:35.000Z",
    "link": "https://www.chinanews.com.cn/cj/2026/03-18/10588965.shtml",
    "guid": "https://www.chinanews.com.cn/cj/2026/03-18/10588965.shtml",
    "author": null,
    "comments": null,
    "origlink": null,
    "image": {},
    "source": {},
    "categories": [],
    "enclosures": []
  },
  {
    "title": "带着作品拓市场 浙江横店影视“借港出海”",
    "description": "中新网金华3月18日电 (刘子琳 陈巧丹 何奕涵)“早就听闻横店拍摄基地多、服务成熟，现在微短剧发展很快，这次过来也想寻找合作机会，切入这个新赛道。”在浙江金华横店展区内，来自深圳的影视公司负责人袁女士一边参观展陈，一边与工作人员交流合作可能。",
    "summary": "中新网金华3月18日电 (刘子琳 陈巧丹 何奕涵)“早就听闻横店拍摄基地多、服务成熟，现在微短剧发展很快，这次过来也想寻找合作机会，切入这个新赛道。”在浙江金华横店展区内，来自深圳的影视公司负责人袁女士一边参观展陈，一边与工作人员交流合作可能。",
    "date": "2026-03-18T11:38:17.000Z",
    "link": "https://www.chinanews.com.cn/cj/2026/03-18/10588963.shtml",
    "guid": "https://www.chinanews.com.cn/cj/2026/03-18/10588963.shtml",
    "author": null,
    "comments": null,
    "origlink": null,
    "image": {},
    "source": {},
    "categories": [],
    "enclosures": []
  },
  {
    "title": "海南产经新观察：乐城先行区构建医疗消费“引力场”",
    "description": "中新网海口3月18日电 (张月和)在18日举行的第六届中国国际消费品博览会新闻发布会上，博鳌乐城国际医疗旅游先行区(简称“乐城先行区”)管理局副局长符祝表示，乐城先行区已连续6年借助中国国际消费品博览会(简称“消博会”)这一国家级平台，构建医疗消费高品质“引力场”。",
    "summary": "中新网海口3月18日电 (张月和)在18日举行的第六届中国国际消费品博览会新闻发布会上，博鳌乐城国际医疗旅游先行区(简称“乐城先行区”)管理局副局长符祝表示，乐城先行区已连续6年借助中国国际消费品博览会(简称“消博会”)这一国家级平台，构建医疗消费高品质“引力场”。",
    "date": "2026-03-18T11:38:15.000Z",
    "link": "https://www.chinanews.com.cn/cj/2026/03-18/10588972.shtml",
    "guid": "https://www.chinanews.com.cn/cj/2026/03-18/10588972.shtml",
    "author": null,
    "comments": null,
    "origlink": null,
    "image": {},
    "source": {},
    "categories": [],
    "enclosures": []
  },
  {
    "title": "甬金铁路新昌北站货场投运 浙江内陆新增开放大通道",
    "description": "中新网绍兴3月18日电(项菁 楼林军)3月18日凌晨，在位于浙江绍兴的甬金铁路新昌北站货场，装载着药品、制冷设备、汽车配件等货物的首列货运列车缓缓驶出，开往宁波舟山港。",
    "summary": "中新网绍兴3月18日电(项菁 楼林军)3月18日凌晨，在位于浙江绍兴的甬金铁路新昌北站货场，装载着药品、制冷设备、汽车配件等货物的首列货运列车缓缓驶出，开往宁波舟山港。",
    "date": "2026-03-18T11:38:07.000Z",
    "link": "https://www.chinanews.com.cn/cj/2026/03-18/10588962.shtml",
    "guid": "https://www.chinanews.com.cn/cj/2026/03-18/10588962.shtml",
    "author": null,
    "comments": null,
    "origlink": null,
    "image": {},
    "source": {},
    "categories": [],
    "enclosures": []
  },
  {
    "title": "消博之约：国际品牌将集聚三亚游艇展 15艘首发首秀",
    "description": "中新网海口3月18日电 (张月和)三亚市人民政府副秘书长吉才冠18日在第六届中国国际消费品博览会(简称“消博会”)新闻发布会上说，第六届消博会继续在三亚设立分会场，打造国际游艇分展区，将有15艘船艇实现国内首发首秀。",
    "summary": "中新网海口3月18日电 (张月和)三亚市人民政府副秘书长吉才冠18日在第六届中国国际消费品博览会(简称“消博会”)新闻发布会上说，第六届消博会继续在三亚设立分会场，打造国际游艇分展区，将有15艘船艇实现国内首发首秀。",
    "date": "2026-03-18T11:37:01.000Z",
    "link": "https://www.chinanews.com.cn/cj/2026/03-18/10588935.shtml",
    "guid": "https://www.chinanews.com.cn/cj/2026/03-18/10588935.shtml",
    "author": null,
    "comments": null,
    "origlink": null,
    "image": {},
    "source": {},
    "categories": [],
    "enclosures": []
  },
  {
    "title": "上交所举办“两会”专题国际路演活动",
    "description": "中新网上海3月18日电 (高志苗)上海证券交易所18日发布消息称，“吸引中长期资金”系列线上路演首场活动近日举办。本次活动聚焦全国“两会”，通过加强与国际投资者沟通交流，分享对宏观经济与资本市场的最新展望。活动主要面向中长期配置型外资，来自欧美、亚太、中东等地的代表性资管机构、托管行、券商等近40家外资机构积极参与。",
    "summary": "中新网上海3月18日电 (高志苗)上海证券交易所18日发布消息称，“吸引中长期资金”系列线上路演首场活动近日举办。本次活动聚焦全国“两会”，通过加强与国际投资者沟通交流，分享对宏观经济与资本市场的最新展望。活动主要面向中长期配置型外资，来自欧美、亚太、中东等地的代表性资管机构、托管行、券商等近40家外资机构积极参与。",
    "date": "2026-03-18T11:36:39.000Z",
    "link": "https://www.chinanews.com.cn/cj/2026/03-18/10588969.shtml",
    "guid": "https://www.chinanews.com.cn/cj/2026/03-18/10588969.shtml",
    "author": null,
    "comments": null,
    "origlink": null,
    "image": {},
    "source": {},
    "categories": [],
    "enclosures": []
  },
  {
    "title": "新疆油田攻克强敏感致密油藏开发难题 CO₂全域驱替技术获重大突破",
    "description": "中新网乌鲁木齐3月18日电 (李海福 高迎春)记者18日从中国石油新疆油田公司获悉，由中国石油新疆油田勘探开发研究院、采油工艺研究院(监理公司)、玛湖勘探开发项目部、采油二厂等单位联合攻关的“强敏感致密油藏CO#8322;全域驱替技术取得重大突破”成果，日前入选2025年度新疆油田公司十大科技进展。",
    "summary": "中新网乌鲁木齐3月18日电 (李海福 高迎春)记者18日从中国石油新疆油田公司获悉，由中国石油新疆油田勘探开发研究院、采油工艺研究院(监理公司)、玛湖勘探开发项目部、采油二厂等单位联合攻关的“强敏感致密油藏CO#8322;全域驱替技术取得重大突破”成果，日前入选2025年度新疆油田公司十大科技进展。",
    "date": "2026-03-18T11:36:09.000Z",
    "link": "https://www.chinanews.com.cn/cj/2026/03-18/10588939.shtml",
    "guid": "https://www.chinanews.com.cn/cj/2026/03-18/10588939.shtml",
    "author": null,
    "comments": null,
    "origlink": null,
    "image": {},
    "source": {},
    "categories": [],
    "enclosures": []
  },
  {
    "title": "2026国际可持续水产养殖大会在福州开幕",
    "description": "中新网福州3月18日电 (郑江洛)18日，由中国渔业协会(CFA)与联合国粮食及农业组织(FAO)联合主办的2026国际可持续水产养殖大会在福州市开幕。",
    "summary": "中新网福州3月18日电 (郑江洛)18日，由中国渔业协会(CFA)与联合国粮食及农业组织(FAO)联合主办的2026国际可持续水产养殖大会在福州市开幕。",
    "date": "2026-03-18T11:33:30.000Z",
    "link": "https://www.chinanews.com.cn/cj/2026/03-18/10588956.shtml",
    "guid": "https://www.chinanews.com.cn/cj/2026/03-18/10588956.shtml",
    "author": null,
    "comments": null,
    "origlink": null,
    "image": {},
    "source": {},
    "categories": [],
    "enclosures": []
  },
  {
    "title": "河南开封加快壮大汽车产业“版图”",
    "description": "中新网开封3月18日电 (刘鹏 左起超)河南开封产城融合示范区汽车零部件产业园内，车间机器轰鸣，生产线高速运转，工人们干劲十足地检查组装着产品，一辆辆装满座椅、保险杠、后桥等零部件的卡车，不间断地发车驶向开封奇瑞、郑州上汽等汽车工厂。",
    "summary": "中新网开封3月18日电 (刘鹏 左起超)河南开封产城融合示范区汽车零部件产业园内，车间机器轰鸣，生产线高速运转，工人们干劲十足地检查组装着产品，一辆辆装满座椅、保险杠、后桥等零部件的卡车，不间断地发车驶向开封奇瑞、郑州上汽等汽车工厂。",
    "date": "2026-03-18T11:33:20.000Z",
    "link": "https://www.chinanews.com.cn/cj/2026/03-18/10588954.shtml",
    "guid": "https://www.chinanews.com.cn/cj/2026/03-18/10588954.shtml",
    "author": null,
    "comments": null,
    "origlink": null,
    "image": {},
    "source": {},
    "categories": [],
    "enclosures": []
  },
  {
    "title": "福鼎白茶开茶季启幕 推动茶文体旅深度融合发展",
    "description": "中新网宁德3月18日电 (记者 叶茂)以“双遗白茶 健康世界”为主题的第十五届福鼎白茶开茶季启动仪式18日在福建省宁德福鼎市点头镇举行，推动茶文体旅深度融合发展。",
    "summary": "中新网宁德3月18日电 (记者 叶茂)以“双遗白茶 健康世界”为主题的第十五届福鼎白茶开茶季启动仪式18日在福建省宁德福鼎市点头镇举行，推动茶文体旅深度融合发展。",
    "date": "2026-03-18T11:33:06.000Z",
    "link": "https://www.chinanews.com.cn/cj/2026/03-18/10588952.shtml",
    "guid": "https://www.chinanews.com.cn/cj/2026/03-18/10588952.shtml",
    "author": null,
    "comments": null,
    "origlink": null,
    "image": {},
    "source": {},
    "categories": [],
    "enclosures": []
  },
  {
    "title": "全球最大24000TEU双燃料动力集装箱船提前7个半月交付",
    "description": "中新网上海3月18日电 (李秋莹)3月17日，沪东中华造船(集团)有限公司(以下简称沪东中华)建造的全球最大24000TEU级液化天然气(LNG)双燃料动力集装箱船“达飞巴黎大皇宫”号，提前7个半月命名交付。这是沪东中华为法国达飞集团建造的第20艘大型集装箱船，为中法两国在绿色航运与高端制造领域的深度合作增添新的典范。",
    "summary": "中新网上海3月18日电 (李秋莹)3月17日，沪东中华造船(集团)有限公司(以下简称沪东中华)建造的全球最大24000TEU级液化天然气(LNG)双燃料动力集装箱船“达飞巴黎大皇宫”号，提前7个半月命名交付。这是沪东中华为法国达飞集团建造的第20艘大型集装箱船，为中法两国在绿色航运与高端制造领域的深度合作增添新的典范。",
    "date": "2026-03-18T11:32:32.000Z",
    "link": "https://www.chinanews.com.cn/cj/2026/03-18/10588945.shtml",
    "guid": "https://www.chinanews.com.cn/cj/2026/03-18/10588945.shtml",
    "author": null,
    "comments": null,
    "origlink": null,
    "image": {},
    "source": {},
    "categories": [],
    "enclosures": []
  }
]