[
  {
    "title": "对随身登机行李收费，有依据吗",
    "description": "近日有旅客反映带20寸行李箱登机，被部分航空公司要求支付费用，且不同航空公司执行标准不一。航空公司对随身登机行李收取费用是否有依据？旅客该如何知晓哪些航空服务包含在票价内，哪些要额外收费？就此，记者采访了有关航空公司和业内专家。",
    "summary": "近日有旅客反映带20寸行李箱登机，被部分航空公司要求支付费用，且不同航空公司执行标准不一。航空公司对随身登机行李收取费用是否有依据？旅客该如何知晓哪些航空服务包含在票价内，哪些要额外收费？就此，记者采访了有关航空公司和业内专家。",
    "date": "2026-06-01T22:59:29.000Z",
    "link": "https://www.chinanews.com.cn/cj/2026/06-02/10632556.shtml",
    "guid": "https://www.chinanews.com.cn/cj/2026/06-02/10632556.shtml",
    "author": null,
    "comments": null,
    "origlink": null,
    "image": {},
    "source": {},
    "categories": [],
    "enclosures": []
  },
  {
    "title": "工业遗产+潮流业态 老电子管厂成为文旅新地标",
    "description": "四川成都东部的东郊记忆时尚产业园，前身是始建于1958年的成都国营红光电子管厂。近年来，当地通过“微改造、精提升”的创新路径，把工业遗产和潮流消费业态深度融合，让老电子管厂成为文旅新地标。",
    "summary": "四川成都东部的东郊记忆时尚产业园，前身是始建于1958年的成都国营红光电子管厂。近年来，当地通过“微改造、精提升”的创新路径，把工业遗产和潮流消费业态深度融合，让老电子管厂成为文旅新地标。",
    "date": "2026-06-01T14:35:37.000Z",
    "link": "https://www.chinanews.com.cn/cj/2026/06-01/10632539.shtml",
    "guid": "https://www.chinanews.com.cn/cj/2026/06-01/10632539.shtml",
    "author": null,
    "comments": null,
    "origlink": null,
    "image": {},
    "source": {},
    "categories": [],
    "enclosures": []
  },
  {
    "title": "一层隔膜的突围：永州凭什么站上锂电新风口？",
    "description": "中新网永州6月1日电 (程春雨 宋宇晟) 电池因针刺、重压等起火燃烧，曾是困扰新能源汽车发展的重要问题。如今，一层膜有效解决了这一问题。",
    "summary": "中新网永州6月1日电 (程春雨 宋宇晟) 电池因针刺、重压等起火燃烧，曾是困扰新能源汽车发展的重要问题。如今，一层膜有效解决了这一问题。",
    "date": "2026-06-01T14:29:19.000Z",
    "link": "https://www.chinanews.com.cn/cj/2026/06-01/10632533.shtml",
    "guid": "https://www.chinanews.com.cn/cj/2026/06-01/10632533.shtml",
    "author": null,
    "comments": null,
    "origlink": null,
    "image": {},
    "source": {},
    "categories": [],
    "enclosures": []
  },
  {
    "title": "尺素金声 | 前4月规上工业企业利润增长18.2%，持续呈现积极向好信号",
    "description": "5月27日，国家统计局发布最新数据显示，今年前4月，全国规上工业企业实现利润同比增长18.2%，增速较一季度加快2.7个百分点，其中4月单月同比增幅达24.7%，展现出强劲的修复态势。",
    "summary": "5月27日，国家统计局发布最新数据显示，今年前4月，全国规上工业企业实现利润同比增长18.2%，增速较一季度加快2.7个百分点，其中4月单月同比增幅达24.7%，展现出强劲的修复态势。",
    "date": "2026-06-01T14:25:12.000Z",
    "link": "https://www.chinanews.com.cn/cj/2026/06-01/10632534.shtml",
    "guid": "https://www.chinanews.com.cn/cj/2026/06-01/10632534.shtml",
    "author": null,
    "comments": null,
    "origlink": null,
    "image": {},
    "source": {},
    "categories": [],
    "enclosures": []
  },
  {
    "title": "中外媒体向浙江提问 三组关系揭示创新“密码”",
    "description": "中新网杭州6月1日电 (张斌)中国国务院新闻办公室6月1日在浙江杭州举行中外记者见面会，浙江省副省长何中伟及相关部门负责人介绍科技创新和产业创新相关情况，并回答记者提问。",
    "summary": "中新网杭州6月1日电 (张斌)中国国务院新闻办公室6月1日在浙江杭州举行中外记者见面会，浙江省副省长何中伟及相关部门负责人介绍科技创新和产业创新相关情况，并回答记者提问。",
    "date": "2026-06-01T14:07:03.000Z",
    "link": "https://www.chinanews.com.cn/cj/2026/06-01/10632524.shtml",
    "guid": "https://www.chinanews.com.cn/cj/2026/06-01/10632524.shtml",
    "author": null,
    "comments": null,
    "origlink": null,
    "image": {},
    "source": {},
    "categories": [],
    "enclosures": []
  },
  {
    "title": "2026世界智能产业博览会｜现场观察：智行天下，何以能动未来",
    "description": "津云新闻讯：5月31日，2026世界智能产业博览会迎来公众开放日，现场人头攒动，气氛热烈。相比2024年在天津举办的那一届，本届智博会有3个尤为深刻的变化。",
    "summary": "津云新闻讯：5月31日，2026世界智能产业博览会迎来公众开放日，现场人头攒动，气氛热烈。相比2024年在天津举办的那一届，本届智博会有3个尤为深刻的变化。",
    "date": "2026-06-01T13:53:32.000Z",
    "link": "https://www.chinanews.com.cn/cj/2026/06-01/10632522.shtml",
    "guid": "https://www.chinanews.com.cn/cj/2026/06-01/10632522.shtml",
    "author": null,
    "comments": null,
    "origlink": null,
    "image": {},
    "source": {},
    "categories": [],
    "enclosures": []
  },
  {
    "title": "宁夏全面推行不动产“数字身份证”",
    "description": "中新网银川6月1日电 (记者 于晶)6月1日起，宁夏全面推行不动产单元代码“一码关联”制度，为每一宗不动产配备专属、唯一、精准的“数字身份证”，贯通不动产从规划、审批到登记使用的全流程，从根源上解决重复申报、多头跑路问题。",
    "summary": "中新网银川6月1日电 (记者 于晶)6月1日起，宁夏全面推行不动产单元代码“一码关联”制度，为每一宗不动产配备专属、唯一、精准的“数字身份证”，贯通不动产从规划、审批到登记使用的全流程，从根源上解决重复申报、多头跑路问题。",
    "date": "2026-06-01T13:27:13.000Z",
    "link": "https://www.chinanews.com.cn/cj/2026/06-01/10632500.shtml",
    "guid": "https://www.chinanews.com.cn/cj/2026/06-01/10632500.shtml",
    "author": null,
    "comments": null,
    "origlink": null,
    "image": {},
    "source": {},
    "categories": [],
    "enclosures": []
  },
  {
    "title": "浙江创新三大智慧监管模式给“幽灵外卖”戴上紧箍咒",
    "description": "中新网杭州6月1日电(奚金燕)6月1日，《网络餐饮服务经营者落实食品安全主体责任监督管理规定》正式施行，筑牢外卖安全防线。作为平台经济大省，2024年下半年开始，浙江以数字化改革为牵引，连出“三招”——从“证照核验比对”到“电子证照公示”，再到“互联网+明厨亮灶”，三项首创智慧监管举措环环相扣，让“看不见的外卖”变成“看得见的厨房”。",
    "summary": "中新网杭州6月1日电(奚金燕)6月1日，《网络餐饮服务经营者落实食品安全主体责任监督管理规定》正式施行，筑牢外卖安全防线。作为平台经济大省，2024年下半年开始，浙江以数字化改革为牵引，连出“三招”——从“证照核验比对”到“电子证照公示”，再到“互联网+明厨亮灶”，三项首创智慧监管举措环环相扣，让“看不见的外卖”变成“看得见的厨房”。",
    "date": "2026-06-01T13:26:37.000Z",
    "link": "https://www.chinanews.com.cn/cj/2026/06-01/10632499.shtml",
    "guid": "https://www.chinanews.com.cn/cj/2026/06-01/10632499.shtml",
    "author": null,
    "comments": null,
    "origlink": null,
    "image": {},
    "source": {},
    "categories": [],
    "enclosures": []
  },
  {
    "title": "中国官方发布非化石能源电力消费核算指南",
    "description": "中新社北京6月1日电 (记者 王梦瑶)为完善碳排放统计核算体系，中国国家发展改革委、国家能源局等五部门6月1日对外公布《非化石能源电力消费核算指南(试行)》(下称《指南》)。",
    "summary": "中新社北京6月1日电 (记者 王梦瑶)为完善碳排放统计核算体系，中国国家发展改革委、国家能源局等五部门6月1日对外公布《非化石能源电力消费核算指南(试行)》(下称《指南》)。",
    "date": "2026-06-01T13:23:23.000Z",
    "link": "https://www.chinanews.com.cn/cj/2026/06-01/10632478.shtml",
    "guid": "https://www.chinanews.com.cn/cj/2026/06-01/10632478.shtml",
    "author": null,
    "comments": null,
    "origlink": null,
    "image": {},
    "source": {},
    "categories": [],
    "enclosures": []
  },
  {
    "title": "2026沈阳机器人大会开幕  中外嘉宾共探智造未来",
    "description": "中新社沈阳6月1日电 (姜月恒 刁海洋 姚小辉)2026沈阳机器人大会6月1日在沈阳举行。中外知名专家学者，韩国、德国、爱尔兰等国家的40余位代表，80余家机器人领域企业负责人，在大会上以“新质引领发展，智造链接未来”为主题展开探讨。",
    "summary": "中新社沈阳6月1日电 (姜月恒 刁海洋 姚小辉)2026沈阳机器人大会6月1日在沈阳举行。中外知名专家学者，韩国、德国、爱尔兰等国家的40余位代表，80余家机器人领域企业负责人，在大会上以“新质引领发展，智造链接未来”为主题展开探讨。",
    "date": "2026-06-01T13:22:30.000Z",
    "link": "https://www.chinanews.com.cn/cj/2026/06-01/10632476.shtml",
    "guid": "https://www.chinanews.com.cn/cj/2026/06-01/10632476.shtml",
    "author": null,
    "comments": null,
    "origlink": null,
    "image": {},
    "source": {},
    "categories": [],
    "enclosures": []
  },
  {
    "title": "中证协召开托管结算与财务会计专业委员会主任委员（扩大）会议",
    "description": "中新网北京6月1日电 (记者 陈康亮)据中国证券业协会(下称中证协)1日消息，中证协托管结算与财务会计专业委员会主任委员(扩大)会议近日召开。会议深入学习贯彻2026年全国两会和“十五五”规划纲要精神，研究部署2026年重点工作。会议由委员会主任委员、东吴证券董事长范力主持，协会相关负责人出席会议并致辞，证监会机构司、中国结算相关同志，以及委员会副主任委员、委员代表等20余人参加会议。",
    "summary": "中新网北京6月1日电 (记者 陈康亮)据中国证券业协会(下称中证协)1日消息，中证协托管结算与财务会计专业委员会主任委员(扩大)会议近日召开。会议深入学习贯彻2026年全国两会和“十五五”规划纲要精神，研究部署2026年重点工作。会议由委员会主任委员、东吴证券董事长范力主持，协会相关负责人出席会议并致辞，证监会机构司、中国结算相关同志，以及委员会副主任委员、委员代表等20余人参加会议。",
    "date": "2026-06-01T13:12:12.000Z",
    "link": "https://www.chinanews.com.cn/cj/2026/06-01/10632457.shtml",
    "guid": "https://www.chinanews.com.cn/cj/2026/06-01/10632457.shtml",
    "author": null,
    "comments": null,
    "origlink": null,
    "image": {},
    "source": {},
    "categories": [],
    "enclosures": []
  },
  {
    "title": "苏辽携手打通产销通道 “辽品入苏、苏品入辽”正式落地",
    "description": "中新网沈阳6月1日电 (记者 李晛)“辽供产品品鉴交流会”近日在沈阳举行。",
    "summary": "中新网沈阳6月1日电 (记者 李晛)“辽供产品品鉴交流会”近日在沈阳举行。",
    "date": "2026-06-01T13:10:36.000Z",
    "link": "https://www.chinanews.com.cn/cj/2026/06-01/10632444.shtml",
    "guid": "https://www.chinanews.com.cn/cj/2026/06-01/10632444.shtml",
    "author": null,
    "comments": null,
    "origlink": null,
    "image": {},
    "source": {},
    "categories": [],
    "enclosures": []
  },
  {
    "title": "知识产权如何赋能科技和产业创新深度融合？业界专家学者聚焦研讨",
    "description": "中新网北京6月1日电 (记者 孙自法)记者6月1日从中国科学院大学(国科大)获悉，2026年适逢其知识产权学院成立十周年，一场主题为“知识产权赋能科技创新和产业创新深度融合”的研讨会暨座谈会近日在北京举行，旨在为深入研究知识产权在科技创新和产业创新中的赋能路径、实践模式与发展趋势，提供理论支撑与智力支持。",
    "summary": "中新网北京6月1日电 (记者 孙自法)记者6月1日从中国科学院大学(国科大)获悉，2026年适逢其知识产权学院成立十周年，一场主题为“知识产权赋能科技创新和产业创新深度融合”的研讨会暨座谈会近日在北京举行，旨在为深入研究知识产权在科技创新和产业创新中的赋能路径、实践模式与发展趋势，提供理论支撑与智力支持。",
    "date": "2026-06-01T13:07:42.000Z",
    "link": "https://www.chinanews.com.cn/cj/2026/06-01/10632466.shtml",
    "guid": "https://www.chinanews.com.cn/cj/2026/06-01/10632466.shtml",
    "author": null,
    "comments": null,
    "origlink": null,
    "image": {},
    "source": {},
    "categories": [],
    "enclosures": []
  },
  {
    "title": "上海机场发布危险品互信社区试点成果 助力上海国际航空货运枢纽能级提升",
    "description": "中新网上海6月1日电 (记者 殷立勤)6月1日，危险品互信社区(DGTC)上海试点成果发布暨空港协商会议机制2026年第一次会议在虹桥机场希尔顿酒店举行，会上发布了上海机场DGTC试点一年来的阶段性成果，推动上海国际货运航空枢纽和全球产业链供应链更高质量发展。",
    "summary": "中新网上海6月1日电 (记者 殷立勤)6月1日，危险品互信社区(DGTC)上海试点成果发布暨空港协商会议机制2026年第一次会议在虹桥机场希尔顿酒店举行，会上发布了上海机场DGTC试点一年来的阶段性成果，推动上海国际货运航空枢纽和全球产业链供应链更高质量发展。",
    "date": "2026-06-01T13:04:32.000Z",
    "link": "https://www.chinanews.com.cn/cj/2026/06-01/10632439.shtml",
    "guid": "https://www.chinanews.com.cn/cj/2026/06-01/10632439.shtml",
    "author": null,
    "comments": null,
    "origlink": null,
    "image": {},
    "source": {},
    "categories": [],
    "enclosures": []
  },
  {
    "title": "第四届“企业商业秘密保护能力提升服务月”活动启动",
    "description": "中新网北京6月1日电 (记者 刘亮)市场监管总局1日在北京举办第四届“企业商业秘密保护能力提升服务月”(以下简称“服务月”)启动仪式。市场监管总局党组成员、副局长，国家标准化管理委员会主任邓志勇出席并讲话。",
    "summary": "中新网北京6月1日电 (记者 刘亮)市场监管总局1日在北京举办第四届“企业商业秘密保护能力提升服务月”(以下简称“服务月”)启动仪式。市场监管总局党组成员、副局长，国家标准化管理委员会主任邓志勇出席并讲话。",
    "date": "2026-06-01T12:45:04.000Z",
    "link": "https://www.chinanews.com.cn/cj/2026/06-01/10632442.shtml",
    "guid": "https://www.chinanews.com.cn/cj/2026/06-01/10632442.shtml",
    "author": null,
    "comments": null,
    "origlink": null,
    "image": {},
    "source": {},
    "categories": [],
    "enclosures": []
  },
  {
    "title": "2026年服贸会将打造“会展+”融合业态",
    "description": "中新网北京6月1日电 (记者 吕少威)2026年中国国际服务贸易交易会(下称“服贸会”)将于9月9日至9月13日在北京首钢园区举办。本届服贸会将打破传统会展场馆的物理边界，把工业遗存更新地标、产业创新成果展示和“吃住行游购娱”有机结合，推出多条会展小镇“游览线路”和服贸会专属促消费活动，打造“会展+”融合业态。",
    "summary": "中新网北京6月1日电 (记者 吕少威)2026年中国国际服务贸易交易会(下称“服贸会”)将于9月9日至9月13日在北京首钢园区举办。本届服贸会将打破传统会展场馆的物理边界，把工业遗存更新地标、产业创新成果展示和“吃住行游购娱”有机结合，推出多条会展小镇“游览线路”和服贸会专属促消费活动，打造“会展+”融合业态。",
    "date": "2026-06-01T12:43:40.000Z",
    "link": "https://www.chinanews.com.cn/cj/2026/06-01/10632431.shtml",
    "guid": "https://www.chinanews.com.cn/cj/2026/06-01/10632431.shtml",
    "author": null,
    "comments": null,
    "origlink": null,
    "image": {},
    "source": {},
    "categories": [],
    "enclosures": []
  },
  {
    "title": "2026年服贸会专题展将融入前沿技术 展示科技消费新成果",
    "description": "中新网北京6月1日电 (记者 吕少威)2026年中国国际服务贸易交易会(下称“服贸会”)总体安排新闻发布会1日在北京举行。北辰集团副总经理魏明乾在发布会上表示，2026年服贸会九大专题展将深度融入前沿技术，注重智慧化场景的打造，展示科技消费的新成果。",
    "summary": "中新网北京6月1日电 (记者 吕少威)2026年中国国际服务贸易交易会(下称“服贸会”)总体安排新闻发布会1日在北京举行。北辰集团副总经理魏明乾在发布会上表示，2026年服贸会九大专题展将深度融入前沿技术，注重智慧化场景的打造，展示科技消费的新成果。",
    "date": "2026-06-01T12:42:44.000Z",
    "link": "https://www.chinanews.com.cn/cj/2026/06-01/10632430.shtml",
    "guid": "https://www.chinanews.com.cn/cj/2026/06-01/10632430.shtml",
    "author": null,
    "comments": null,
    "origlink": null,
    "image": {},
    "source": {},
    "categories": [],
    "enclosures": []
  },
  {
    "title": "40余个国家和国际组织确认2026年服贸会设展办会",
    "description": "中新社北京6月1日电 (记者 吕少威)2026年中国国际服务贸易交易会(简称“服贸会”)将于9月9日至13日在北京首钢园区举办。目前，挪威、澳大利亚、国际竹藤组织等40余个国家和国际组织已确认将以国家或总部名义设展办会，沃尔玛、西门子、礼来、强生等250余家企业机构将参展。",
    "summary": "中新社北京6月1日电 (记者 吕少威)2026年中国国际服务贸易交易会(简称“服贸会”)将于9月9日至13日在北京首钢园区举办。目前，挪威、澳大利亚、国际竹藤组织等40余个国家和国际组织已确认将以国家或总部名义设展办会，沃尔玛、西门子、礼来、强生等250余家企业机构将参展。",
    "date": "2026-06-01T12:27:05.000Z",
    "link": "https://www.chinanews.com.cn/cj/2026/06-01/10632417.shtml",
    "guid": "https://www.chinanews.com.cn/cj/2026/06-01/10632417.shtml",
    "author": null,
    "comments": null,
    "origlink": null,
    "image": {},
    "source": {},
    "categories": [],
    "enclosures": []
  },
  {
    "title": "上海前瞻布局服务业新兴赛道",
    "description": "中新社上海6月1日电 (记者 郑莹莹)“开局起步‘十五五’”系列主题上海市政府新闻发布会于6月1日举行。上海多部门介绍了《上海市服务业发展“十五五”规划》的有关情况。该规划指出，上海前瞻布局服务业新兴赛道，挖掘未来发展新潜力。",
    "summary": "中新社上海6月1日电 (记者 郑莹莹)“开局起步‘十五五’”系列主题上海市政府新闻发布会于6月1日举行。上海多部门介绍了《上海市服务业发展“十五五”规划》的有关情况。该规划指出，上海前瞻布局服务业新兴赛道，挖掘未来发展新潜力。",
    "date": "2026-06-01T12:24:33.000Z",
    "link": "https://www.chinanews.com.cn/cj/2026/06-01/10632416.shtml",
    "guid": "https://www.chinanews.com.cn/cj/2026/06-01/10632416.shtml",
    "author": null,
    "comments": null,
    "origlink": null,
    "image": {},
    "source": {},
    "categories": [],
    "enclosures": []
  },
  {
    "title": "5月中国百城新房价格环比微涨 二手房价降幅收窄",
    "description": "中新社北京6月1日电 (记者 庞无忌)5月份，中国主要城市房价延续回稳势头。",
    "summary": "中新社北京6月1日电 (记者 庞无忌)5月份，中国主要城市房价延续回稳势头。",
    "date": "2026-06-01T12:22:45.000Z",
    "link": "https://www.chinanews.com.cn/cj/2026/06-01/10632415.shtml",
    "guid": "https://www.chinanews.com.cn/cj/2026/06-01/10632415.shtml",
    "author": null,
    "comments": null,
    "origlink": null,
    "image": {},
    "source": {},
    "categories": [],
    "enclosures": []
  },
  {
    "title": "夏日美食湖北小龙虾热销海外",
    "description": "中新社武汉6月1日电 (武一力 熊皖扬 张阮璐)记者1日从武汉海关获悉，夏日来临，湖北小龙虾成为颇受食客青睐的“顶流”美食，热销海外市场。湖北小龙虾等特色水产外贸，正从初级产品外销向“品质+品牌”双向升级。",
    "summary": "中新社武汉6月1日电 (武一力 熊皖扬 张阮璐)记者1日从武汉海关获悉，夏日来临，湖北小龙虾成为颇受食客青睐的“顶流”美食，热销海外市场。湖北小龙虾等特色水产外贸，正从初级产品外销向“品质+品牌”双向升级。",
    "date": "2026-06-01T11:33:28.000Z",
    "link": "https://www.chinanews.com.cn/cj/2026/06-01/10632396.shtml",
    "guid": "https://www.chinanews.com.cn/cj/2026/06-01/10632396.shtml",
    "author": null,
    "comments": null,
    "origlink": null,
    "image": {},
    "source": {},
    "categories": [],
    "enclosures": []
  },
  {
    "title": "以政务、物流、金融之变 奏响义乌改革开放“进行曲”",
    "description": "中新网义乌6月1日电(周健)义乌市国际贸易服务中心内，外商往来如梭，AI多语翻译机实时切换多国语言，政务服务效率显著提升；义乌(苏溪)国际枢纽港一片繁忙作业景象，集装箱整齐排列，货物办完手续即视同进入宁波舟山港；“义支付”后台，一串串跨境结算数据快速跳动，为中小微企业筑牢资金安全防线……",
    "summary": "中新网义乌6月1日电(周健)义乌市国际贸易服务中心内，外商往来如梭，AI多语翻译机实时切换多国语言，政务服务效率显著提升；义乌(苏溪)国际枢纽港一片繁忙作业景象，集装箱整齐排列，货物办完手续即视同进入宁波舟山港；“义支付”后台，一串串跨境结算数据快速跳动，为中小微企业筑牢资金安全防线……",
    "date": "2026-06-01T11:22:01.000Z",
    "link": "https://www.chinanews.com.cn/cj/2026/06-01/10632374.shtml",
    "guid": "https://www.chinanews.com.cn/cj/2026/06-01/10632374.shtml",
    "author": null,
    "comments": null,
    "origlink": null,
    "image": {},
    "source": {},
    "categories": [],
    "enclosures": []
  },
  {
    "title": "市场监管总局：严厉打击“携密跳槽”“恶意挖角”等行为",
    "description": "中新网6月1日电 据“市说新语”微信公众号消息，6月1日，市场监管总局在北京举办第四届“企业商业秘密保护能力提升服务月”(以下简称“服务月”)启动仪式。",
    "summary": "中新网6月1日电 据“市说新语”微信公众号消息，6月1日，市场监管总局在北京举办第四届“企业商业秘密保护能力提升服务月”(以下简称“服务月”)启动仪式。",
    "date": "2026-06-01T11:20:49.000Z",
    "link": "https://www.chinanews.com.cn/cj/2026/06-01/10632400.shtml",
    "guid": "https://www.chinanews.com.cn/cj/2026/06-01/10632400.shtml",
    "author": null,
    "comments": null,
    "origlink": null,
    "image": {},
    "source": {},
    "categories": [],
    "enclosures": []
  },
  {
    "title": "蒙内铁路通车九载 中车齐车护航东非动脉畅行",
    "description": "中新网哈尔滨6月1日电 (史轶夫 刘廷禄)记者6月1日从中车齐齐哈尔车辆有限公司(以下简称“中车齐车公司”)获悉，蒙巴萨至内罗毕标准轨距铁路(以下简称“蒙内铁路”)开通九周年来，中车齐车公司以持续深耕的装备保障与运维服务，成为铁路安全运营背后坚实的中国力量。",
    "summary": "中新网哈尔滨6月1日电 (史轶夫 刘廷禄)记者6月1日从中车齐齐哈尔车辆有限公司(以下简称“中车齐车公司”)获悉，蒙巴萨至内罗毕标准轨距铁路(以下简称“蒙内铁路”)开通九周年来，中车齐车公司以持续深耕的装备保障与运维服务，成为铁路安全运营背后坚实的中国力量。",
    "date": "2026-06-01T11:20:25.000Z",
    "link": "https://www.chinanews.com.cn/cj/2026/06-01/10632391.shtml",
    "guid": "https://www.chinanews.com.cn/cj/2026/06-01/10632391.shtml",
    "author": null,
    "comments": null,
    "origlink": null,
    "image": {},
    "source": {},
    "categories": [],
    "enclosures": []
  },
  {
    "title": "中外企业在渝发起NCD公约创新实践“全球倡议”",
    "description": "中新网重庆6月1日电 (张旭)6月1日，“规则共筑·生态共建”推动NCD公约创新实践倡议(下称“倡议”)在重庆发起。",
    "summary": "中新网重庆6月1日电 (张旭)6月1日，“规则共筑·生态共建”推动NCD公约创新实践倡议(下称“倡议”)在重庆发起。",
    "date": "2026-06-01T11:16:51.000Z",
    "link": "https://www.chinanews.com.cn/cj/2026/06-01/10632364.shtml",
    "guid": "https://www.chinanews.com.cn/cj/2026/06-01/10632364.shtml",
    "author": null,
    "comments": null,
    "origlink": null,
    "image": {},
    "source": {},
    "categories": [],
    "enclosures": []
  },
  {
    "title": "市场监管总局发布一批儿童相关国家标准",
    "description": "中新网6月1日电 据市场监管总局网站消息，近日，市场监管总局发布一批儿童相关国家标准，涉及毛绒玩具、电动童车、儿童伞具、未成年人上网等方面，从儿童用品到网络环境全面升级技术要求，多层次筑牢儿童安全防护屏障。",
    "summary": "中新网6月1日电 据市场监管总局网站消息，近日，市场监管总局发布一批儿童相关国家标准，涉及毛绒玩具、电动童车、儿童伞具、未成年人上网等方面，从儿童用品到网络环境全面升级技术要求，多层次筑牢儿童安全防护屏障。",
    "date": "2026-06-01T11:13:20.000Z",
    "link": "https://www.chinanews.com.cn/cj/2026/06-01/10632399.shtml",
    "guid": "https://www.chinanews.com.cn/cj/2026/06-01/10632399.shtml",
    "author": null,
    "comments": null,
    "origlink": null,
    "image": {},
    "source": {},
    "categories": [],
    "enclosures": []
  },
  {
    "title": "突破行业壁垒  国产动捕技术实现百人同步实时捕捉",
    "description": "中新网上海6月1日电 (记者 许婧)“100人，同时进入数字世界”百人实时动作捕捉挑战暨数字动作展演5月31日在上海落幕。活动成功实现百人同场实时动作捕捉，在1000平方米大空间场景下稳定运行，达成12毫秒超低延迟，刷新全球公开实时多人动作捕捉纪录。",
    "summary": "中新网上海6月1日电 (记者 许婧)“100人，同时进入数字世界”百人实时动作捕捉挑战暨数字动作展演5月31日在上海落幕。活动成功实现百人同场实时动作捕捉，在1000平方米大空间场景下稳定运行，达成12毫秒超低延迟，刷新全球公开实时多人动作捕捉纪录。",
    "date": "2026-06-01T11:12:26.000Z",
    "link": "https://www.chinanews.com.cn/cj/2026/06-01/10632387.shtml",
    "guid": "https://www.chinanews.com.cn/cj/2026/06-01/10632387.shtml",
    "author": null,
    "comments": null,
    "origlink": null,
    "image": {},
    "source": {},
    "categories": [],
    "enclosures": []
  },
  {
    "title": "覆盖20多国优质商品  上海举办“丝路云品”选品会",
    "description": "中新网上海6月1日电 (记者 姜煜)“丝路云品”选品会暨2026上海“丝路云品”直播电商周启动仪式1日在虹桥国际中央商务区举行。",
    "summary": "中新网上海6月1日电 (记者 姜煜)“丝路云品”选品会暨2026上海“丝路云品”直播电商周启动仪式1日在虹桥国际中央商务区举行。",
    "date": "2026-06-01T11:09:20.000Z",
    "link": "https://www.chinanews.com.cn/cj/2026/06-01/10632378.shtml",
    "guid": "https://www.chinanews.com.cn/cj/2026/06-01/10632378.shtml",
    "author": null,
    "comments": null,
    "origlink": null,
    "image": {},
    "source": {},
    "categories": [],
    "enclosures": []
  },
  {
    "title": "阿迪达斯夹克可用于“在城里办事”？客服：相关商品页面已修改优化",
    "description": "中新网6月1日电(记者 吴家驹)近日，多位网友反映，阿迪达斯的一款夹克外套，商品介绍中包含“在城里办事”，此事引起广泛争议。",
    "summary": "中新网6月1日电(记者 吴家驹)近日，多位网友反映，阿迪达斯的一款夹克外套，商品介绍中包含“在城里办事”，此事引起广泛争议。",
    "date": "2026-06-01T10:56:23.000Z",
    "link": "https://www.chinanews.com.cn/cj/2026/06-01/10632375.shtml",
    "guid": "https://www.chinanews.com.cn/cj/2026/06-01/10632375.shtml",
    "author": null,
    "comments": null,
    "origlink": null,
    "image": {},
    "source": {},
    "categories": [],
    "enclosures": []
  },
  {
    "title": "闲鱼会自动上传用户手机照片到闲鱼空间？客服否认",
    "description": "中新网6月1日电(记者 吴家驹)近日，有用户反映，自己手机内的文物照片，被闲鱼自动生成为商品上架售卖，引发广泛关注。6月1日，记者就此事以用户身份咨询闲鱼客服，对方表示，该事件需要对方(当事人)联系客服核实。",
    "summary": "中新网6月1日电(记者 吴家驹)近日，有用户反映，自己手机内的文物照片，被闲鱼自动生成为商品上架售卖，引发广泛关注。6月1日，记者就此事以用户身份咨询闲鱼客服，对方表示，该事件需要对方(当事人)联系客服核实。",
    "date": "2026-06-01T10:53:25.000Z",
    "link": "https://www.chinanews.com.cn/cj/2026/06-01/10632373.shtml",
    "guid": "https://www.chinanews.com.cn/cj/2026/06-01/10632373.shtml",
    "author": null,
    "comments": null,
    "origlink": null,
    "image": {},
    "source": {},
    "categories": [],
    "enclosures": []
  }
]